ami_crypto_next.py
ami_crypto_next-0.1.1.dist-info/METADATA
ami_crypto_next-0.1.1.dist-info/WHEEL
ami_crypto_next-0.1.1.dist-info/top_level.txt
ami_crypto_next-0.1.1.dist-info/RECORD
