Metadata-Version: 2.4
Name: ami-crypto-next
Version: 0.1.1
Summary: 国家电网内网系统《电力采集系统2.0》的相关加解密支持
Author-email: Author Name <email@tmd.wtf>
License-Expression: MIT
Project-URL: Homepage, https://example.com/
Keywords: SM2,SM3,SM4,AES,crypto,State Grid,AMI,SGCC
Classifier: Programming Language :: Python :: 3
Classifier: Operating System :: OS Independent
Classifier: Topic :: Security :: Cryptography
Requires-Python: >=3.8
Requires-Dist: gmssl>=3.2.2
Requires-Dist: pycryptodome>=3.20.0
